[
  {
    "reviewer_name": "H.j. Van Loon",
    "rating": 5,
    "review_text": "Grafkelder van Limburg Stirum",
    "review_date": "2024-07-06T17:48:45.354Z",
    "reviewer_image": "https://lh3.googleusercontent.com/a-/ALV-UjVCoeIKzRFRTolalSgCNoIk982NceDMN2CCxYnoJqkOSHiiYMmH8g=s120-c-rp-mo-ba4-br100"
  },
  {
    "reviewer_name": "Hyperion",
    "rating": 4,
    "review_text": "Mooie begraafplaats in een rustgevende omgeving.",
    "review_date": "2024-08-13T07:04:27.210Z",
    "reviewer_image": "https://lh3.googleusercontent.com/a-/ALV-UjX4lVDf0uNotjXNql00SIooG1_UKFBJiOlbYsDzGLIrDTgDfiE=s120-c-rp-mo-ba5-br100"
  },
  {
    "reviewer_name": "G.W. van Lonkhuyzen",
    "rating": 5,
    "review_text": "Prachtige plek in Oranjewoud. Historisch, statig en laagdrempelig tegelijkertijd.",
    "review_date": "2021-03-12T22:11:02.144Z",
    "reviewer_image": "https://lh3.googleusercontent.com/a/ACg8ocIgSuKQOvfHrZ8J1kaHfb9MxRetx8531hpHWrpx09GG1-TWEAw=s120-c-rp-mo-ba6-br100"
  },
  {
    "reviewer_name": "Aale Van Der Heide",
    "rating": 4,
    "review_text": "Begraafplaats 🙂",
    "review_date": "2023-09-24T14:57:43.601Z",
    "reviewer_image": "https://lh3.googleusercontent.com/a-/ALV-UjVBtgS49p_hjrlrxdLyQGOkxxvEBwta_lAh4vGOjakPzKe75AwLPg=s120-c-rp-mo-ba8-br100"
  }
]