[
  {
    "reviewer_name": "Peter Ankone",
    "rating": 5,
    "review_text": "Wel een nette rustige begraafplaats goed onderhouden.",
    "review_date": "2025-11-20T18:01:58.551Z",
    "reviewer_image": "https://lh3.googleusercontent.com/a/ACg8ocJznTI8iw_2tStWKVzuG9v6H-_2GebgqkLSBp0ci-rjAN5CkA=s120-c-rp-mo-ba2-br100"
  },
  {
    "reviewer_name": "Joop Vzwaaij",
    "rating": 5,
    "review_text": "Mooi en verzorgde begraafplaats",
    "review_date": "2020-07-02T14:40:36.855Z",
    "reviewer_image": "https://lh3.googleusercontent.com/a-/ALV-UjX8X4p6Fvubp1ChgfhSVEyUzmaf4xR1KlqTuUUD0PWgggSdIoARqA=s120-c-rp-mo-ba5-br100"
  },
  {
    "reviewer_name": "Wiellie Muldery",
    "rating": 5,
    "review_text": "de,hoeve,passartweg,hoensbroek",
    "review_date": "2021-02-14T15:22:24.042Z",
    "reviewer_image": "https://lh3.googleusercontent.com/a-/ALV-UjU6Yc0C7V8c5GJ1J6GBSgl9DIf0z1wuD37j45lmoZ6tR92POlE=s120-c-rp-mo-br100"
  }
]